deepl_scraper_pp/__init__.py
deepl_scraper_pp/deepl_tr.py
deepl_scraper_pp/get_ppbrowser.py
deepl_scraper_pp-0.1.2.dist-info/WHEEL
deepl_scraper_pp-0.1.2.dist-info/METADATA
deepl_scraper_pp-0.1.2.dist-info/RECORD
