Metadata-Version: 2.1
Name: deepl-scraper-pp
Version: 0.1.2
Summary: scrape deepl via pyppeteer
Home-page: https://github.com/ffreemt/deepl-scraper-pyppeteer
License: MIT
Author: freemt
Requires-Python: >=3.7,<4.0
Classifier: License :: OSI Approved :: MIT License
Classifier: Programming Language :: Python :: 3
Classifier: Programming Language :: Python :: 3.7
Classifier: Programming Language :: Python :: 3.8
Classifier: Programming Language :: Python :: 3.9
Requires-Dist: get-ppbrowser (>=0.1.3,<0.2.0)
Requires-Dist: linetimer (>=0.1.4,<0.2.0)
Requires-Dist: logzero (>=1.6.3,<2.0.0)
Requires-Dist: pyquery (>=1.4.3,<2.0.0)
Project-URL: Repository, https://github.com/ffreemt/deepl-scraper-pyppeteer
